graylint/__init__.py
graylint/__main__.py
graylint/command_line.py
graylint/config.py
graylint/help.py
graylint/linting.py
graylint/py.typed
graylint/version.py
graylint/tests/test_command_line.py
graylint/tests/test_linting.py
graylint/tests/test_main.py
graylint-2.0.0.dist-info/LICENSE.rst
graylint-2.0.0.dist-info/METADATA
graylint-2.0.0.dist-info/WHEEL
graylint-2.0.0.dist-info/entry_points.txt
graylint-2.0.0.dist-info/top_level.txt
graylint-2.0.0.dist-info/RECORD
