Metadata-Version: 2.1
Name: graylint
Version: 2.0.0
Summary: Run linters and show only new errors compared to an older commit
Home-page: https://github.com/akaihola/graylint
Author: Antti Kaihola
Author-email: 13725+akaihola@users.noreply.github.com
License: BSD
Project-URL: Source Code, https://github.com/akaihola/graylint
Project-URL: Change Log, https://github.com/akaihola/graylint/blob/master/CHANGES.rst
Project-URL: News, https://github.com/akaihola/graylint/discussions/categories/announcements
Classifier: Programming Language :: Python :: 3 :: Only
Classifier: Programming Language :: Python :: 3.8
Classifier: Programming Language :: Python :: 3.9
Classifier: Programming Language :: Python :: 3.10
Classifier: Programming Language :: Python :: 3.11
Classifier: Programming Language :: Python :: 3.12
Requires-Python: >=3.8
License-File: LICENSE.rst
Requires-Dist: darkgraylib ~=2.0.0
Provides-Extra: color
Requires-Dist: Pygments >=2.4.0 ; extra == 'color'
Provides-Extra: release
Requires-Dist: darkgray-dev-tools ~=0.1.1 ; extra == 'release'
Provides-Extra: test
Requires-Dist: click >=8.0.0 ; extra == 'test'
Requires-Dist: cryptography >=3.3.2 ; extra == 'test'
Requires-Dist: defusedxml >=0.7.1 ; extra == 'test'
Requires-Dist: mypy >=0.990 ; extra == 'test'
Requires-Dist: pathspec ; extra == 'test'
Requires-Dist: pip-requirements-parser ; extra == 'test'
Requires-Dist: pydocstyle ; extra == 'test'
Requires-Dist: Pygments >=2.4.0 ; extra == 'test'
Requires-Dist: pylint ; extra == 'test'
Requires-Dist: pytest >=6.2.0 ; extra == 'test'
Requires-Dist: pytest-kwparametrize >=0.0.3 ; extra == 'test'
Requires-Dist: requests-cache >=0.7 ; extra == 'test'
Requires-Dist: ruamel.yaml >=0.17.21 ; extra == 'test'
Requires-Dist: ruff >=0.0.292 ; extra == 'test'
Requires-Dist: twine >=2.0.0 ; extra == 'test'
Requires-Dist: types-requests >=2.27.9 ; extra == 'test'
Requires-Dist: types-toml >=0.10.4 ; extra == 'test'
Requires-Dist: urllib3 >=1.25.9 ; extra == 'test'
Requires-Dist: wheel >=0.21.0 ; extra == 'test'
